kapybara/__init__.py
kapybara/form_element.py
kapybara/hightlight_text.py
kapybara/runtime_counter.py
kapybara/shared_data.py
kapybara/shortcuts.py
kapybara/tool.py
kapybara/browserlib/CrossIframeFinder.py
kapybara/browserlib/__init__.py
kapybara/browserlib/custom_browser.py
kapybara/browserlib/prevent_sleep.py
kapybara/browserlib/加解密.py
kapybara/common/__init__.py
kapybara/common/envWrite.py
kapybara/common/excel_create.py
kapybara/common/write_excel.py
soda_kapybara-2025.7.30.2.dist-info/METADATA
soda_kapybara-2025.7.30.2.dist-info/WHEEL
soda_kapybara-2025.7.30.2.dist-info/RECORD
