Metadata-Version: 2.4
Name: soda_kapybara
Version: 2025.7.30.2
Summary: 卡皮巴拉浏览器库
Requires-Python: >=3.12
Requires-Dist: cryptography>=45.0.5
Requires-Dist: ddddocr>=1.4.2
Requires-Dist: numpy>=2.3.1
Requires-Dist: openpyxl>=3.1.5
Requires-Dist: pandas>=2.3.1
Requires-Dist: pydantic>=2.11.7
Requires-Dist: pytest>=8.4.1
Requires-Dist: requests>=2.32.4
Requires-Dist: selenium>=4.34.2
Requires-Dist: yxmb-compatlib>=2025.7.30.5
